aprxc.py
aprxc-2.0.2.dist-info/METADATA
aprxc-2.0.2.dist-info/WHEEL
aprxc-2.0.2.dist-info/entry_points.txt
aprxc-2.0.2.dist-info/licenses/LICENSE
aprxc-2.0.2.dist-info/RECORD
