Metadata-Version: 2.4
Name: aprxc
Version: 2.0.2
Summary: A command-line tool to estimate the number of distinct lines in a file/stream using Chakraborty/Vinodchandran/Meel’s approximation algorithm.
Project-URL: Codeberg, https://codeberg.org/fa81/aprxc
Project-URL: GitHub, https://github.com/hellp/aprxc
Author-email: Fabian Neumann <dev@fabianneumann.de>
License-File: LICENSE
Keywords: algorithm,cli,computer-science,math
Classifier: Development Status :: 4 - Beta
Classifier: Intended Audience :: Developers
Classifier: Intended Audience :: Science/Research
Classifier: License :: OSI Approved :: European Union Public Licence 1.2 (EUPL 1.2)
Classifier: Programming Language :: Python :: 3
Classifier: Programming Language :: Python :: 3.11
Classifier: Programming Language :: Python :: 3.12
Classifier: Programming Language :: Python :: 3.13
Classifier: Topic :: Scientific/Engineering :: Mathematics
Classifier: Topic :: Utilities
Requires-Python: >=3.11
